src/__init__.py
src/linker.py
src/menus.py
src/read.py
src/tracking.py
src/utils.py
src/characterisation/__init__.py
src/characterisation/gr.py
src/characterisation/msd.py
src/characterisation/overlap.py
src/characterisation/psi6.py
src/plots/__black_pink__.py
src/plots/__blue_pink__.py
src/plots/__blues__.py
src/plots/__init__.py
src/plots/__pink_blue__.py
src/plots/__purple_banana__.py
src/plots/__quichi__.py
src/plots/__teal_peach__.py
src/plots/plots.py
src/plots/sans_serif.py
particle_tracking-0.0.0.dist-info/LICENSE.txt
particle_tracking-0.0.0.dist-info/METADATA
particle_tracking-0.0.0.dist-info/WHEEL
particle_tracking-0.0.0.dist-info/top_level.txt
particle_tracking-0.0.0.dist-info/RECORD
