Metadata-Version: 2.1
Name: particle-tracking
Version: 0.0.0
Summary: Particle tracking algorithm for 2-Dimensional experiments
Home-page: 
Author: Abraham Mauleon Amieva
Author-email: abrhm.ma@gmail.com
Classifier: Programming Language :: Python
Classifier: Operating System :: OS Independent
License-File: LICENSE.txt
